my_own_package/__init__.py
alex_moldovan_first_package-0.2.0.dist-info/METADATA
alex_moldovan_first_package-0.2.0.dist-info/WHEEL
alex_moldovan_first_package-0.2.0.dist-info/top_level.txt
alex_moldovan_first_package-0.2.0.dist-info/RECORD
