Metadata-Version: 2.1
Name: alex-moldovan-first-package
Version: 0.2.0
Summary: my_first_package
Author: Alex Moldovan
Author-email: alex_moldovan1@yahoo.com
